ez_storage/__init__.py
ez_storage/ez_storage.py
ez_storage-1.3.3.dist-info/METADATA
ez_storage-1.3.3.dist-info/WHEEL
ez_storage-1.3.3.dist-info/top_level.txt
ez_storage-1.3.3.dist-info/RECORD
