Metadata-Version: 2.1
Name: ez-storage
Version: 1.3.3
Summary: mostly it is a dependency
Home-page: https://github.com/Lainupcomputer/ez-storage
Author: LainupComuter(Sandro Kalett)
Author-email: kontakt@lainupcomputersolution.de
Project-URL: Bug Tracker, https://github.com/Lainupcomputer/ez-storage/issues
Classifier: Programming Language :: Python :: 3
Classifier: License :: OSI Approved :: MIT License
Classifier: Operating System :: OS Independent
Requires-Python: >=3.9
